Workbook

Sheet Аналоги
A1: АНАЛИЗ АНАЛОГОВ (КОНКУРЕНТЫ) — объект:
A2: Жёлтое заполняет ассистент, серое считается само. Каждое объявление — строка + скриншот в папку «Аналитика» (объявления снимают). Цена аренды — ₽ в месяц за весь объект (ЦИАН для коммерции показывает ₽/м² в ГОД — пересчитать).
A4: НАШ ОБЪЕКТ | D4: ИТОГ
A5: Объект | D5: Аналогов учтено | E5: =SUM($AD$21:$AD$60)
A6: Адрес | D6: Средневзвешенная цена, ₽ за м² | E6: =IF(E5=0,"",SUMPRODUCT($AC$21:$AC$60,$AB$21:$AB$60))
A7: Сделка | B7: Продажа | D7: Рыночная цена объекта, ₽ | E7: =IFERROR(E6*$B$9,"")
A8: Тип / назначение | D8: Диапазон: от, ₽ | E8: =IF(E5=0,"",_xlfn.MINIFS($AC$21:$AC$60,$AD$21:$AD$60,1)*$B$9)
A9: Площадь, м² | D9: Диапазон: до, ₽ | E9: =IF(E5=0,"",_xlfn.MAXIFS($AC$21:$AC$60,$AD$21:$AD$60,1)*$B$9)
A10: Ремонт | B10: С ремонтом (без мебели) | D10: Коэффициент вариации (≤ 20 % — выборка однородная) | E10: =IF(E5<2,"",SQRT(SUMPRODUCT($AD$21:$AD$60,($AC$21:$AC$60-SUM($AC$21:$AC$60)/E5)^2)/(E5-1))/(SUM($AC$21:$AC$60)/E5))
A11: Этаж / вход | D11: Цена собственника к рынку | E11: =IFERROR($B$12/E7-1,"")
A12: Цена собственника, ₽ | D12: Средний срок экспозиции учтённых, дней | E12: =IFERROR(SUMPRODUCT($AD$21:$AD$60,$F$21:$F$60)/SUMPRODUCT($AD$21:$AD$60,--($F$21:$F$60<>"")),"")
A13: Дата анализа | D13: Вывод | E13: =IF(E5<3,"Мало аналогов — расширьте поиск (уровень 2–3)",IF(E10>0.2,"Выборка разнородная — пересмотрите аналоги и корректировки",IF(E11>0.1,"Цена собственника выше рынка более чем на 10 %",IF(E11<-0.1,"Цена собственника ниже рынка более чем на 10 %","Цена собственника в рынке"))))
A14: Класс объекта | B14: Комфорт
A19: АНАЛОГИ | P19: КОРРЕКТИРОВКИ (порядок: торг → площадь → ремонт → местоположение, этаж, прочее)
A20: № | B20: Уровень (1/2/3) | C20: Ссылка на объявление | D20: Дата сбора | E20: Статус | F20: Дней в экспозиции | G20: Адрес / ЖК / посёлок | H20: Расстояние до нашего, км | I20: Тип / назначение | J20: Площадь, м² | K20: Участок, сот. (дома) | L20: Этаж / вход | M20: Ремонт | N20: Особенности: чем лучше (+) / хуже (−) нашего | O20: Цена предложения, ₽ (аренда — ₽/мес) | P20: Цена за м², ₽ | Q20: Торг, % | R20: Площадь, % | S20: Ремонт, ₽ за м² | T20: Местоположение, % | U20: Этаж / вход / тип, % | V20: Прочее (парковка, вид, участок, мебель), % | W20: Обоснование ручных корректировок | X20: Скорректированная цена за м², ₽ | Y20: Общая корректировка без ремонта, % | Z20: Учитываем? | AA20: Вес (сырой) | AB20: Вес | AC20: служ.: цена учтённого | AD20: служ.: учтён
A21: 1 | P21: =IF($O21="","",O21/J21) | Q21: =IF($O21="","",IF(E21="Сделка",0,-Параметры!$B$3)) | R21: =IF($O21="","",IF(ABS(J21/$B$9-1)<=Параметры!$B$5,0,($B$9/J21)^Параметры!$B$4-1)) | S21: =IF($O21="","",IFERROR(VLOOKUP($B$10,Параметры!$A$10:$D$12,IF($B$7="Аренда",4,IF($B$14="Премиум",3,2)),FALSE)-VLOOKUP(M21,Параметры!$A$10:$D$12,IF($B$7="Аренда",4,IF($B$14="Премиум",3,2)),FALSE),0)) | X21: =IF($O21="","",(P21*(1+Q21)*(1+R21)+S21)*(1+N(T21))*(1+N(U21))*(1+N(V21))) | Y21: =IF($O21="","",ABS(Q21)+ABS(R21)+ABS(N(T21))+ABS(N(U21))+ABS(N(V21))) | Z21: =IF($O21="","",IF(Y21>Параметры!$B$6,"Нет — корректировки > предела","Да")) | AA21: =IF($O21="","",IF(Z21="Да",IFERROR(VLOOKUP(B21,Параметры!$A$17:$B$19,2,FALSE),0.4)/(Y21+ABS(S21/(P21*(1+Q21)))+0.1),0)) | AB21: =IFERROR(AA21/SUM($AA$21:$AA$60),0) | AC21: =IF(Z21="Да",X21,0) | AD21: =IF(Z21="Да",1,0)
A22: 2 | P22: =IF($O22="","",O22/J22) | Q22: =IF($O22="","",IF(E22="Сделка",0,-Параметры!$B$3)) | R22: =IF($O22="","",IF(ABS(J22/$B$9-1)<=Параметры!$B$5,0,($B$9/J22)^Параметры!$B$4-1)) | S22: =IF($O22="","",IFERROR(VLOOKUP($B$10,Параметры!$A$10:$D$12,IF($B$7="Аренда",4,IF($B$14="Премиум",3,2)),FALSE)-VLOOKUP(M22,Параметры!$A$10:$D$12,IF($B$7="Аренда",4,IF($B$14="Премиум",3,2)),FALSE),0)) | X22: =IF($O22="","",(P22*(1+Q22)*(1+R22)+S22)*(1+N(T22))*(1+N(U22))*(1+N(V22))) | Y22: =IF($O22="","",ABS(Q22)+ABS(R22)+ABS(N(T22))+ABS(N(U22))+ABS(N(V22))) | Z22: =IF($O22="","",IF(Y22>Параметры!$B$6,"Нет — корректировки > предела","Да")) | AA22: =IF($O22="","",IF(Z22="Да",IFERROR(VLOOKUP(B22,Параметры!$A$17:$B$19,2,FALSE),0.4)/(Y22+ABS(S22/(P22*(1+Q22)))+0.1),0)) | AB22: =IFERROR(AA22/SUM($AA$21:$AA$60),0) | AC22: =IF(Z22="Да",X22,0) | AD22: =IF(Z22="Да",1,0)
A23: 3 | P23: =IF($O23="","",O23/J23) | Q23: =IF($O23="","",IF(E23="Сделка",0,-Параметры!$B$3)) | R23: =IF($O23="","",IF(ABS(J23/$B$9-1)<=Параметры!$B$5,0,($B$9/J23)^Параметры!$B$4-1)) | S23: =IF($O23="","",IFERROR(VLOOKUP($B$10,Параметры!$A$10:$D$12,IF($B$7="Аренда",4,IF($B$14="Премиум",3,2)),FALSE)-VLOOKUP(M23,Параметры!$A$10:$D$12,IF($B$7="Аренда",4,IF($B$14="Премиум",3,2)),FALSE),0)) | X23: =IF($O23="","",(P23*(1+Q23)*(1+R23)+S23)*(1+N(T23))*(1+N(U23))*(1+N(V23))) | Y23: =IF($O23="","",ABS(Q23)+ABS(R23)+ABS(N(T23))+ABS(N(U23))+ABS(N(V23))) | Z23: =IF($O23="","",IF(Y23>Параметры!$B$6,"Нет — корректировки > предела","Да")) | AA23: =IF($O23="","",IF(Z23="Да",IFERROR(VLOOKUP(B23,Параметры!$A$17:$B$19,2,FALSE),0.4)/(Y23+ABS(S23/(P23*(1+Q23)))+0.1),0)) | AB23: =IFERROR(AA23/SUM($AA$21:$AA$60),0) | AC23: =IF(Z23="Да",X23,0) | AD23: =IF(Z23="Да",1,0)
A24: 4 | P24: =IF($O24="","",O24/J24) | Q24: =IF($O24="","",IF(E24="Сделка",0,-Параметры!$B$3)) | R24: =IF($O24="","",IF(ABS(J24/$B$9-1)<=Параметры!$B$5,0,($B$9/J24)^Параметры!$B$4-1)) | S24: =IF($O24="","",IFERROR(VLOOKUP($B$10,Параметры!$A$10:$D$12,IF($B$7="Аренда",4,IF($B$14="Премиум",3,2)),FALSE)-VLOOKUP(M24,Параметры!$A$10:$D$12,IF($B$7="Аренда",4,IF($B$14="Премиум",3,2)),FALSE),0)) | X24: =IF($O24="","",(P24*(1+Q24)*(1+R24)+S24)*(1+N(T24))*(1+N(U24))*(1+N(V24))) | Y24: =IF($O24="","",ABS(Q24)+ABS(R24)+ABS(N(T24))+ABS(N(U24))+ABS(N(V24))) | Z24: =IF($O24="","",IF(Y24>Параметры!$B$6,"Нет — корректировки > предела","Да")) | AA24: =IF($O24="","",IF(Z24="Да",IFERROR(VLOOKUP(B24,Параметры!$A$17:$B$19,2,FALSE),0.4)/(Y24+ABS(S24/(P24*(1+Q24)))+0.1),0)) | AB24: =IFERROR(AA24/SUM($AA$21:$AA$60),0) | AC24: =IF(Z24="Да",X24,0) | AD24: =IF(Z24="Да",1,0)
A25: 5 | P25: =IF($O25="","",O25/J25) | Q25: =IF($O25="","",IF(E25="Сделка",0,-Параметры!$B$3)) | R25: =IF($O25="","",IF(ABS(J25/$B$9-1)<=Параметры!$B$5,0,($B$9/J25)^Параметры!$B$4-1)) | S25: =IF($O25="","",IFERROR(VLOOKUP($B$10,Параметры!$A$10:$D$12,IF($B$7="Аренда",4,IF($B$14="Премиум",3,2)),FALSE)-VLOOKUP(M25,Параметры!$A$10:$D$12,IF($B$7="Аренда",4,IF($B$14="Премиум",3,2)),FALSE),0)) | X25: =IF($O25="","",(P25*(1+Q25)*(1+R25)+S25)*(1+N(T25))*(1+N(U25))*(1+N(V25))) | Y25: =IF($O25="","",ABS(Q25)+ABS(R25)+ABS(N(T25))+ABS(N(U25))+ABS(N(V25))) | Z25: =IF($O25="","",IF(Y25>Параметры!$B$6,"Нет — корректировки > предела","Да")) | AA25: =IF($O25="","",IF(Z25="Да",IFERROR(VLOOKUP(B25,Параметры!$A$17:$B$19,2,FALSE),0.4)/(Y25+ABS(S25/(P25*(1+Q25)))+0.1),0)) | AB25: =IFERROR(AA25/SUM($AA$21:$AA$60),0) | AC25: =IF(Z25="Да",X25,0) | AD25: =IF(Z25="Да",1,0)
A26: 6 | P26: =IF($O26="","",O26/J26) | Q26: =IF($O26="","",IF(E26="Сделка",0,-Параметры!$B$3)) | R26: =IF($O26="","",IF(ABS(J26/$B$9-1)<=Параметры!$B$5,0,($B$9/J26)^Параметры!$B$4-1)) | S26: =IF($O26="","",IFERROR(VLOOKUP($B$10,Параметры!$A$10:$D$12,IF($B$7="Аренда",4,IF($B$14="Премиум",3,2)),FALSE)-VLOOKUP(M26,Параметры!$A$10:$D$12,IF($B$7="Аренда",4,IF($B$14="Премиум",3,2)),FALSE),0)) | X26: =IF($O26="","",(P26*(1+Q26)*(1+R26)+S26)*(1+N(T26))*(1+N(U26))*(1+N(V26))) | Y26: =IF($O26="","",ABS(Q26)+ABS(R26)+ABS(N(T26))+ABS(N(U26))+ABS(N(V26))) | Z26: =IF($O26="","",IF(Y26>Параметры!$B$6,"Нет — корректировки > предела","Да")) | AA26: =IF($O26="","",IF(Z26="Да",IFERROR(VLOOKUP(B26,Параметры!$A$17:$B$19,2,FALSE),0.4)/(Y26+ABS(S26/(P26*(1+Q26)))+0.1),0)) | AB26: =IFERROR(AA26/SUM($AA$21:$AA$60),0) | AC26: =IF(Z26="Да",X26,0) | AD26: =IF(Z26="Да",1,0)
A27: 7 | P27: =IF($O27="","",O27/J27) | Q27: =IF($O27="","",IF(E27="Сделка",0,-Параметры!$B$3)) | R27: =IF($O27="","",IF(ABS(J27/$B$9-1)<=Параметры!$B$5,0,($B$9/J27)^Параметры!$B$4-1)) | S27: =IF($O27="","",IFERROR(VLOOKUP($B$10,Параметры!$A$10:$D$12,IF($B$7="Аренда",4,IF($B$14="Премиум",3,2)),FALSE)-VLOOKUP(M27,Параметры!$A$10:$D$12,IF($B$7="Аренда",4,IF($B$14="Премиум",3,2)),FALSE),0)) | X27: =IF($O27="","",(P27*(1+Q27)*(1+R27)+S27)*(1+N(T27))*(1+N(U27))*(1+N(V27))) | Y27: =IF($O27="","",ABS(Q27)+ABS(R27)+ABS(N(T27))+ABS(N(U27))+ABS(N(V27))) | Z27: =IF($O27="","",IF(Y27>Параметры!$B$6,"Нет — корректировки > предела","Да")) | AA27: =IF($O27="","",IF(Z27="Да",IFERROR(VLOOKUP(B27,Параметры!$A$17:$B$19,2,FALSE),0.4)/(Y27+ABS(S27/(P27*(1+Q27)))+0.1),0)) | AB27: =IFERROR(AA27/SUM($AA$21:$AA$60),0) | AC27: =IF(Z27="Да",X27,0) | AD27: =IF(Z27="Да",1,0)
A28: 8 | P28: =IF($O28="","",O28/J28) | Q28: =IF($O28="","",IF(E28="Сделка",0,-Параметры!$B$3)) | R28: =IF($O28="","",IF(ABS(J28/$B$9-1)<=Параметры!$B$5,0,($B$9/J28)^Параметры!$B$4-1)) | S28: =IF($O28="","",IFERROR(VLOOKUP($B$10,Параметры!$A$10:$D$12,IF($B$7="Аренда",4,IF($B$14="Премиум",3,2)),FALSE)-VLOOKUP(M28,Параметры!$A$10:$D$12,IF($B$7="Аренда",4,IF($B$14="Премиум",3,2)),FALSE),0)) | X28: =IF($O28="","",(P28*(1+Q28)*(1+R28)+S28)*(1+N(T28))*(1+N(U28))*(1+N(V28))) | Y28: =IF($O28="","",ABS(Q28)+ABS(R28)+ABS(N(T28))+ABS(N(U28))+ABS(N(V28))) | Z28: =IF($O28="","",IF(Y28>Параметры!$B$6,"Нет — корректировки > предела","Да")) | AA28: =IF($O28="","",IF(Z28="Да",IFERROR(VLOOKUP(B28,Параметры!$A$17:$B$19,2,FALSE),0.4)/(Y28+ABS(S28/(P28*(1+Q28)))+0.1),0)) | AB28: =IFERROR(AA28/SUM($AA$21:$AA$60),0) | AC28: =IF(Z28="Да",X28,0) | AD28: =IF(Z28="Да",1,0)
A29: 9 | P29: =IF($O29="","",O29/J29) | Q29: =IF($O29="","",IF(E29="Сделка",0,-Параметры!$B$3)) | R29: =IF($O29="","",IF(ABS(J29/$B$9-1)<=Параметры!$B$5,0,($B$9/J29)^Параметры!$B$4-1)) | S29: =IF($O29="","",IFERROR(VLOOKUP($B$10,Параметры!$A$10:$D$12,IF($B$7="Аренда",4,IF($B$14="Премиум",3,2)),FALSE)-VLOOKUP(M29,Параметры!$A$10:$D$12,IF($B$7="Аренда",4,IF($B$14="Премиум",3,2)),FALSE),0)) | X29: =IF($O29="","",(P29*(1+Q29)*(1+R29)+S29)*(1+N(T29))*(1+N(U29))*(1+N(V29))) | Y29: =IF($O29="","",ABS(Q29)+ABS(R29)+ABS(N(T29))+ABS(N(U29))+ABS(N(V29))) | Z29: =IF($O29="","",IF(Y29>Параметры!$B$6,"Нет — корректировки > предела","Да")) | AA29: =IF($O29="","",IF(Z29="Да",IFERROR(VLOOKUP(B29,Параметры!$A$17:$B$19,2,FALSE),0.4)/(Y29+ABS(S29/(P29*(1+Q29)))+0.1),0)) | AB29: =IFERROR(AA29/SUM($AA$21:$AA$60),0) | AC29: =IF(Z29="Да",X29,0) | AD29: =IF(Z29="Да",1,0)
A30: 10 | P30: =IF($O30="","",O30/J30) | Q30: =IF($O30="","",IF(E30="Сделка",0,-Параметры!$B$3)) | R30: =IF($O30="","",IF(ABS(J30/$B$9-1)<=Параметры!$B$5,0,($B$9/J30)^Параметры!$B$4-1)) | S30: =IF($O30="","",IFERROR(VLOOKUP($B$10,Параметры!$A$10:$D$12,IF($B$7="Аренда",4,IF($B$14="Премиум",3,2)),FALSE)-VLOOKUP(M30,Параметры!$A$10:$D$12,IF($B$7="Аренда",4,IF($B$14="Премиум",3,2)),FALSE),0)) | X30: =IF($O30="","",(P30*(1+Q30)*(1+R30)+S30)*(1+N(T30))*(1+N(U30))*(1+N(V30))) | Y30: =IF($O30="","",ABS(Q30)+ABS(R30)+ABS(N(T30))+ABS(N(U30))+ABS(N(V30))) | Z30: =IF($O30="","",IF(Y30>Параметры!$B$6,"Нет — корректировки > предела","Да")) | AA30: =IF($O30="","",IF(Z30="Да",IFERROR(VLOOKUP(B30,Параметры!$A$17:$B$19,2,FALSE),0.4)/(Y30+ABS(S30/(P30*(1+Q30)))+0.1),0)) | AB30: =IFERROR(AA30/SUM($AA$21:$AA$60),0) | AC30: =IF(Z30="Да",X30,0) | AD30: =IF(Z30="Да",1,0)
A31: 11 | P31: =IF($O31="","",O31/J31) | Q31: =IF($O31="","",IF(E31="Сделка",0,-Параметры!$B$3)) | R31: =IF($O31="","",IF(ABS(J31/$B$9-1)<=Параметры!$B$5,0,($B$9/J31)^Параметры!$B$4-1)) | S31: =IF($O31="","",IFERROR(VLOOKUP($B$10,Параметры!$A$10:$D$12,IF($B$7="Аренда",4,IF($B$14="Премиум",3,2)),FALSE)-VLOOKUP(M31,Параметры!$A$10:$D$12,IF($B$7="Аренда",4,IF($B$14="Премиум",3,2)),FALSE),0)) | X31: =IF($O31="","",(P31*(1+Q31)*(1+R31)+S31)*(1+N(T31))*(1+N(U31))*(1+N(V31))) | Y31: =IF($O31="","",ABS(Q31)+ABS(R31)+ABS(N(T31))+ABS(N(U31))+ABS(N(V31))) | Z31: =IF($O31="","",IF(Y31>Параметры!$B$6,"Нет — корректировки > предела","Да")) | AA31: =IF($O31="","",IF(Z31="Да",IFERROR(VLOOKUP(B31,Параметры!$A$17:$B$19,2,FALSE),0.4)/(Y31+ABS(S31/(P31*(1+Q31)))+0.1),0)) | AB31: =IFERROR(AA31/SUM($AA$21:$AA$60),0) | AC31: =IF(Z31="Да",X31,0) | AD31: =IF(Z31="Да",1,0)
A32: 12 | P32: =IF($O32="","",O32/J32) | Q32: =IF($O32="","",IF(E32="Сделка",0,-Параметры!$B$3)) | R32: =IF($O32="","",IF(ABS(J32/$B$9-1)<=Параметры!$B$5,0,($B$9/J32)^Параметры!$B$4-1)) | S32: =IF($O32="","",IFERROR(VLOOKUP($B$10,Параметры!$A$10:$D$12,IF($B$7="Аренда",4,IF($B$14="Премиум",3,2)),FALSE)-VLOOKUP(M32,Параметры!$A$10:$D$12,IF($B$7="Аренда",4,IF($B$14="Премиум",3,2)),FALSE),0)) | X32: =IF($O32="","",(P32*(1+Q32)*(1+R32)+S32)*(1+N(T32))*(1+N(U32))*(1+N(V32))) | Y32: =IF($O32="","",ABS(Q32)+ABS(R32)+ABS(N(T32))+ABS(N(U32))+ABS(N(V32))) | Z32: =IF($O32="","",IF(Y32>Параметры!$B$6,"Нет — корректировки > предела","Да")) | AA32: =IF($O32="","",IF(Z32="Да",IFERROR(VLOOKUP(B32,Параметры!$A$17:$B$19,2,FALSE),0.4)/(Y32+ABS(S32/(P32*(1+Q32)))+0.1),0)) | AB32: =IFERROR(AA32/SUM($AA$21:$AA$60),0) | AC32: =IF(Z32="Да",X32,0) | AD32: =IF(Z32="Да",1,0)
... A60: 40 | P60: =IF($O60="","",O60/J60) | Q60: =IF($O60="","",IF(E60="Сделка",0,-Параметры!$B$3)) | R60: =IF($O60="","",IF(ABS(J60/$B$9-1)<=Параметры!$B$5,0,($B$9/J60)^Параметры!$B$4-1)) | S60: =IF($O60="","",IFERROR(VLOOKUP($B$10,Параметры!$A$10:$D$12,IF($B$7="Аренда",4,IF($B$14="Премиум",3,2)),FALSE)-VLOOKUP(M60,Параметры!$A$10:$D$12,IF($B$7="Аренда",4,IF($B$14="Премиум",3,2)),FALSE),0)) | X60: =IF($O60="","",(P60*(1+Q60)*(1+R60)+S60)*(1+N(T60))*(1+N(U60))*(1+N(V60))) | Y60: =IF($O60="","",ABS(Q60)+ABS(R60)+ABS(N(T60))+ABS(N(U60))+ABS(N(V60))) | Z60: =IF($O60="","",IF(Y60>Параметры!$B$6,"Нет — корректировки > предела","Да")) | AA60: =IF($O60="","",IF(Z60="Да",IFERROR(VLOOKUP(B60,Параметры!$A$17:$B$19,2,FALSE),0.4)/(Y60+ABS(S60/(P60*(1+Q60)))+0.1),0)) | AB60: =IFERROR(AA60/SUM($AA$21:$AA$60),0) | AC60: =IF(Z60="Да",X60,0) | AD60: =IF(Z60="Да",1,0)

Sheet Параметры
A1: ПАРАМЕТРЫ КОРРЕКТИРОВОК — жёлтые ячейки можно менять (ориентиры, утверждает брокер)
A3: Скидка на торг, % (продажа: жильё 3–5, коммерция 5–10, загородные 7–12; аренда 3–5) | B3: 0.05
A4: Коэффициент торможения на площадь (коммерция −0,15; квартиры −0,10; дома −0,20) | B4: -0.15
A5: Разница площадей без корректировки, % (меньше — не корректируем) | B5: 0.1
A6: Предельная общая корректировка аналога, % (больше — аналог не учитываем) | B6: 0.3
A8: РЕМОНТ — стоимость отделки от нуля, БЕЗ мебели (класс объекта — в блоке «Наш объект»)
A9: Уровень | B9: Комфорт, ₽ за м² | C9: Премиум, ₽ за м² | D9: Аренда, ₽ за м² в месяц
A10: Без отделки | B10: 0 | C10: 0 | D10: 0
A11: Предчистовая (white box) | B11: 12000 | C11: 12000 | D11: 50
A12: С ремонтом (без мебели) | B12: 100000 | C12: 250000 | D12: 150
A13: Мебель и техника в корректировку ремонта не входят — если у аналога есть мебель, это ручная корректировка «Прочее».
A16: ВЕС ПО УРОВНЮ СОПОСТАВИМОСТИ
A17: 1 | B17: 1 | C17: 1 — прямой конкурент (та же локация, тип, площадь ±30 %)
A18: 2 | B18: 0.7 | C18: 2 — расширенный поиск (соседний район / площадь ±50 % / снятые до 6 мес.)
A19: 3 | B19: 0.4 | C19: 3 — дальний аналог (другая локация того же класса / снятые до 12 мес.)

Sheet Как заполнять
A1: КАК ЗАПОЛНЯТЬ (подробно — инструкция «09 — Анализ конкурентов» в 03_ИНСТРУКЦИИ)
A2: 1. Сделайте копию шаблона в папку объекта «Аналитика»: «Анализ аналогов — <объект> — дд.мм.гггг».
A3: 2. Заполните блок «Наш объект» (сделка, площадь, ремонт, класс — обязательно). Ремонт: комфорт — 100 000 ₽/м², премиум — 250 000 ₽/м², без мебели.
A4: 3. ЦИАН: те же тип и сделка, та же локация, площадь ±30 %. Сортировка по дате. Минимум 5 прямых аналогов (уровень 1).
A5: 4. Если прямых меньше 5 — расширяйте по шагам: радиус → площадь ±50 % → снятые объявления до 6–12 мес. → другая локация того же класса. Уровень ставьте 2 или 3.
A6: 5. По каждому объявлению: ссылка, скриншот, площадь, ремонт, этаж/вход, цена, дней в экспозиции, особенности (+/−).
A7: 6. Корректировки на торг, площадь и ремонт считаются сами. Местоположение, этаж/вход и прочее ставит брокер (в % с обоснованием).
A8: 7. Аналог с общей корректировкой больше 30 % (без учёта ремонта) не учитывается автоматически. Разница в ремонте снижает вес аналога.
A9: 8. Итог (справа вверху): средневзвешенная цена за м², цена объекта, диапазон, однородность, сравнение с ценой собственника.
A10: 9. Файл → в Claude с промптом «Анализ цены по аналогам» → ответ «Вставить стратегию из Claude».
